live_static_server/__init__.py
live_static_server/__main__.py
live_static_server/cli.py
live_static_server/config.py
live_static_server/watcher.py
live_static_server/server/__init__.py
live_static_server/server/app.py
live_static_server/server/html_handler.py
live_static_server/server/live-static-server.js
live_static_server/server/socket_handler.py
live_static_server-0.0.4.dist-info/LICENSE
live_static_server-0.0.4.dist-info/METADATA
live_static_server-0.0.4.dist-info/WHEEL
live_static_server-0.0.4.dist-info/entry_points.txt
live_static_server-0.0.4.dist-info/top_level.txt
live_static_server-0.0.4.dist-info/RECORD
