Metadata-Version: 2.1
Name: live-static-server
Version: 0.0.4
Summary: live static server
Home-page: https://github.com/qiu8310/live-static-server
Author: Mora
Author-email: qiuzhongleiabc@126.com
Project-URL: Bug Tracker, https://github.com/qiu8310/live-static-server/issues
Classifier: Programming Language :: Python :: 3
Classifier: License :: OSI Approved :: MIT License
Classifier: Operating System :: OS Independent
License-File: LICENSE
Requires-Dist: tornado (>=6)
Requires-Dist: click (>=8)
Requires-Dist: watchdog (>=2)
Requires-Dist: beautifulsoup4 (>=4)
